{
  "project_info": {
    "project_number": "197857435433",
    "project_id": "optimapp-d0d0a",
    "storage_bucket": "optimapp-d0d0a.appspot.com"
  },
  "client": [
    {
      "client_info": {
        "mobilesdk_app_id": "1:197857435433:android:0be5fedb9a477334f2a138",
        "android_client_info": {
          "package_name": "com.silvia.optimapp"
        }
      },
      "oauth_client": [],
      "api_key": [
        {
          "current_key": "AIzaSyAIJpM9-gur7pPsCS_MhFq-8DYKZMx8Ask"
        }
      ],
      "services": {
        "appinvite_service": {
          "other_platform_oauth_client": []
        }
      }
    }
  ],
  "configuration_version": "1"
}